EasyGlobals/EasyGlobals.py
EasyGlobals/__init__.py
easyglobals-0.1.1.dist-info/METADATA
easyglobals-0.1.1.dist-info/WHEEL
easyglobals-0.1.1.dist-info/licenses/LICENSE
easyglobals-0.1.1.dist-info/RECORD
