Metadata-Version: 2.1
Name: EasyGlobals
Version: 0.1.1
Summary: An easy to use variable sharing library for Python using Memcached to can quickly share complex objects between processes as if they had shared memory.
Project-URL: Homepage, https://github.com/YacobBY/Easy_Globals
Project-URL: Bug Tracker, https://github.com/YacobBY/Easy_Globals/issues
Author-email: Y <asnaeb2@gmail.com>
License-File: LICENSE
Keywords: Globals,Python,Shared memory
Classifier: License :: OSI Approved :: MIT License
Classifier: Operating System :: OS Independent
Classifier: Programming Language :: Python :: 3
Requires-Python: >=3.7
Requires-Dist: pymemcache
